tupleleapai-0.0.3b0.dist-info/METADATA
tupleleapai-0.0.3b0.dist-info/WHEEL
tupleleapai.libs/libcrypto-8173d9ca.so.3
tupleleapai.libs/libssl-fa9d51fe.so.3
tupleleapai/__init__.py
tupleleapai/tupleleapai.cpython-310-x86_64-linux-gnu.so
tupleleapai-0.0.3b0.dist-info/RECORD
